{
  "generator-jhipster": {
    "promptValues": {
      "packageName": "com.anelsoftware.clothes",
      "nativeLanguage": "es"
    },
    "jhipsterVersion": "4.2.0",
    "baseName": "anelapi",
    "packageName": "com.anelsoftware.clothes",
    "packageFolder": "com/anelsoftware/clothes",
    "serverPort": "8081",
    "authenticationType": "jwt",
    "hibernateCache": "hazelcast",
    "clusteredHttpSession": false,
    "websocket": false,
    "databaseType": "sql",
    "devDatabaseType": "mysql",
    "prodDatabaseType": "mysql",
    "searchEngine": false,
    "messageBroker": false,
    "serviceDiscoveryType": "eureka",
    "buildTool": "maven",
    "enableSocialSignIn": false,
    "jwtSecretKey": "7f621d9f7402c1e00a8b3c432c7b8d9461a33ef2",
    "enableTranslation": true,
    "applicationType": "microservice",
    "testFrameworks": [
      "gatling",
      "cucumber"
    ],
    "jhiPrefix": "jhi",
    "skipClient": true,
    "skipUserManagement": true,
    "nativeLanguage": "es",
    "languages": [
      "es",
      "en"
    ],
    "clientPackageManager": "yarn"
  }
}